pydatamail_ml/__init__.py
pydatamail_ml/_version.py
pydatamail_ml/machinelearning.py
pydatamail_ml/textprocessing.py
pydatamail_ml-0.0.3.dist-info/LICENSE
pydatamail_ml-0.0.3.dist-info/METADATA
pydatamail_ml-0.0.3.dist-info/WHEEL
pydatamail_ml-0.0.3.dist-info/top_level.txt
pydatamail_ml-0.0.3.dist-info/RECORD
