Metadata-Version: 2.1
Name: pydatamail-ml
Version: 0.0.3
Summary: pydatamail_ml - Machine Learning extension for pydatamail
Home-page: https://github.com/pyscioffice/pydatamail_ml
Author: Jan Janssen
Author-email: jan.janssen@outlook.com
License: BSD
License-File: LICENSE
Requires-Dist: bleach (>=5.0.1)
Requires-Dist: cssutils (>=2.5.0)
Requires-Dist: langdetect (>=1.0.9)
Requires-Dist: numpy (>=1.23.1)
Requires-Dist: pandas (>=1.4.3)
Requires-Dist: pydatamail (>=0.0.9)
Requires-Dist: scikit-learn (>=1.1.1)
Requires-Dist: sqlalchemy (>=1.4.39)
Requires-Dist: tqdm (>=4.64.0)
